dvc_webdav/__init__.py
dvc_webdav/_dvc_webdav_version.py
dvc_webdav/tests/__init__.py
dvc_webdav/tests/cloud.py
dvc_webdav/tests/conftest.py
dvc_webdav/tests/fixtures.py
dvc_webdav/tests/test_dvc.py
dvc_webdav-3.0.0.dist-info/LICENSE
dvc_webdav-3.0.0.dist-info/METADATA
dvc_webdav-3.0.0.dist-info/WHEEL
dvc_webdav-3.0.0.dist-info/top_level.txt
dvc_webdav-3.0.0.dist-info/RECORD
